pycsob/__init__.py
pycsob/client.py
pycsob/conf.py
pycsob/utils.py
pycsob-0.3.1.dist-info/DESCRIPTION.rst
pycsob-0.3.1.dist-info/METADATA
pycsob-0.3.1.dist-info/RECORD
pycsob-0.3.1.dist-info/WHEEL
pycsob-0.3.1.dist-info/metadata.json
pycsob-0.3.1.dist-info/top_level.txt
tests_pycsob/__init__.py
tests_pycsob/test_api.py
tests_pycsob/fixtures/test.key
