Metadata-Version: 2.0
Name: pycsob
Version: 0.3.1
Summary: Python client for ČSOB Payment Gateway
Home-page: https://github.com/TwistoPayments/pycsob
Author: Twisto
Author-email: devs@twisto.cz
License: MIT
Platform: UNKNOWN
Classifier: Development Status :: 4 - Beta
Classifier: Operating System :: OS Independent
Classifier: Programming Language :: Python
Classifier: Programming Language :: Python :: 2
Classifier: Programming Language :: Python :: 2.7
Classifier: Programming Language :: Python :: 3
Classifier: Programming Language :: Python :: 3.5
Classifier: Topic :: Utilities
Requires-Dist: requests (>=2.9.0)
Requires-Dist: pycryptodome (~=3.4.0)
